fullresattn/__init__.py
fullresattn/data/__init__.py
fullresattn/data/data.py
fullresattn/data/pm25selsample.csv
fullresattn/data/simdata.csv
fullresattn/data/simulatedata.py
fullresattn/model/__init__.py
fullresattn/model/fullresatt.py
fullresattn/model/pmetrics.py
fullresattn-0.1.0.data/data/csv/pm25selsample.csv
fullresattn-0.1.0.data/data/csv/simdata.csv
fullresattn-0.1.0.dist-info/LICENSE
fullresattn-0.1.0.dist-info/METADATA
fullresattn-0.1.0.dist-info/WHEEL
fullresattn-0.1.0.dist-info/top_level.txt
fullresattn-0.1.0.dist-info/RECORD
