Metadata-Version: 2.1
Name: fullresattn
Version: 0.1.0
Summary: Library for full residual deep network with attention layers
Home-page: UNKNOWN
Author: Lianfa Li
Author-email: lspatial@gmail.com
License: UNKNOWN
Platform: UNKNOWN
Classifier: Development Status :: 6 - Mature
Classifier: Intended Audience :: Science/Research
Classifier: License :: OSI Approved :: MIT License
Classifier: Programming Language :: Python :: 3
Classifier: Programming Language :: Python :: 3.3
Classifier: Programming Language :: Python :: 3.4
Classifier: Programming Language :: Python :: 3.5
